django_typst/__init__.py
django_typst/config.py
django_typst/encoding.py
django_typst/engine.py
django_typst/py.typed
django_typst-0.1.5.dist-info/licenses/LICENSE
django_typst-0.1.5.dist-info/WHEEL
django_typst-0.1.5.dist-info/METADATA
django_typst-0.1.5.dist-info/RECORD
