Metadata-Version: 2.4
Name: django-typst
Version: 0.1.5
Summary: A Django template engine powered by Typst
Author: Jonathan Moss
Author-email: Jonathan Moss <xirisr@gmail.com>
License-Expression: BSD-3-Clause
License-File: LICENSE
Classifier: Development Status :: 4 - Beta
Classifier: Environment :: Web Environment
Classifier: Framework :: Django
Classifier: Framework :: Django :: 5.2
Classifier: Framework :: Django :: 6.0
Classifier: Intended Audience :: Developers
Classifier: License :: OSI Approved :: BSD License
Classifier: Operating System :: OS Independent
Classifier: Programming Language :: Python
Classifier: Programming Language :: Python :: 3
Classifier: Programming Language :: Python :: 3 :: Only
Classifier: Programming Language :: Python :: 3.12
Classifier: Programming Language :: Python :: 3.13
Classifier: Programming Language :: Python :: 3.14
Classifier: Topic :: Internet :: WWW/HTTP
Classifier: Topic :: Printing
Classifier: Topic :: Software Development :: Libraries
Requires-Dist: django>=5.2.0
Requires-Dist: tomlkit>=0.13.3
Requires-Dist: typst>=0.14.1
Requires-Python: >=3.12, <3.15
Project-URL: Documentation, https://django-typst-engine.readthedocs.io/en/latest/
Project-URL: Homepage, https://github.com/a-musing-moose/django-typst-engine/
Project-URL: Readme, https://github.com/a-musing-moose/django-typst-engine/blob/master/README.md
Project-URL: Repository, https://github.com/a-musing-moose/django-typst-engine/
